btd/sphinx/graphviz.py
btd.sphinx.graphviz-2.3.1.post1.dist-info/LICENSE.md
btd.sphinx.graphviz-2.3.1.post1.dist-info/METADATA
btd.sphinx.graphviz-2.3.1.post1.dist-info/WHEEL
btd.sphinx.graphviz-2.3.1.post1.dist-info/top_level.txt
btd.sphinx.graphviz-2.3.1.post1.dist-info/RECORD
