Metadata-Version: 2.1
Name: btd.sphinx.graphviz
Version: 2.3.1.post1
Summary: Embedding diagrams rendered with Graphviz.
Home-page: https://github.com/buildthedocs/sphinx.graphviz
Author: Sphinx team, Patrick Lehmann
Author-email: Paebbels@gmail.com
License: UNKNOWN
Project-URL: Documentation, https://btd-sphinx-graphviz.readthedocs.io/en/latest/
Project-URL: Source Code, https://github.com/buildthedocs/sphinx.graphviz
Project-URL: Issue Tracker, https://github.com/buildthedocs/sphinx.graphviz/issues
Keywords: Sphinx Documentation Graphviz
Platform: UNKNOWN
Classifier: License :: OSI Approved :: BSD License
Classifier: Operating System :: OS Independent
Classifier: Programming Language :: Python :: 3 :: Only
Classifier: Programming Language :: Python :: 3.4
Classifier: Programming Language :: Python :: 3.5
Classifier: Programming Language :: Python :: 3.6
Classifier: Programming Language :: Python :: 3.7
Classifier: Programming Language :: Python :: 3.8
Classifier: Development Status :: 5 - Production/Stable
Classifier: Intended Audience :: Developers
Classifier: Topic :: Documentation :: Sphinx
Classifier: Framework :: Sphinx :: Extension
Requires-Python: >=3.4
Requires-Dist: sphinx (>=2.3.1)
